odoo/addons/partner_multi_name/README.rst
odoo/addons/partner_multi_name/__init__.py
odoo/addons/partner_multi_name/__manifest__.py
odoo/addons/partner_multi_name/.vscode/settings.json
odoo/addons/partner_multi_name/i18n/es CO.po
odoo/addons/partner_multi_name/i18n/es.po
odoo/addons/partner_multi_name/i18n/partner_multi_name.pot
odoo/addons/partner_multi_name/i18n/partner_other_names.pot
odoo/addons/partner_multi_name/models/__init__.py
odoo/addons/partner_multi_name/models/res_config_settings.py
odoo/addons/partner_multi_name/models/res_partner.py
odoo/addons/partner_multi_name/models/res_users.py
odoo/addons/partner_multi_name/static/description/icon.png
odoo/addons/partner_multi_name/views/res_partner_views.xml
odoo/addons/partner_multi_name/views/res_users_views.xml
odoo11_addon_partner_multi_name-11.0.1.0.0.99.dev5.dist-info/METADATA
odoo11_addon_partner_multi_name-11.0.1.0.0.99.dev5.dist-info/WHEEL
odoo11_addon_partner_multi_name-11.0.1.0.0.99.dev5.dist-info/top_level.txt
odoo11_addon_partner_multi_name-11.0.1.0.0.99.dev5.dist-info/RECORD
